scripts/__init__.py
scripts/add_copyright_headers.sh
scripts/build_installer.py
scripts/build_installer_cli.py
scripts/build_wheels.sh
scripts/common.py
scripts/deps_bundle.py
scripts/find_installbuilder.py
scripts/install_submitter.py
deadline/vred_submitter/VRED_RenderScript_DeadlineCloud.py
deadline/vred_submitter/__init__.py
deadline/vred_submitter/_version.py
deadline/vred_submitter/assets.py
deadline/vred_submitter/constants.py
deadline/vred_submitter/data_classes.py
deadline/vred_submitter/default_vred_job_template.yaml
deadline/vred_submitter/qt_components.py
deadline/vred_submitter/qt_utils.py
deadline/vred_submitter/scene.py
deadline/vred_submitter/utils.py
deadline/vred_submitter/vred_logger.py
deadline/vred_submitter/vred_submitter.py
deadline/vred_submitter/vred_submitter_wrapper.py
deadline/vred_submitter/vred_utils.py
deadline/vred_submitter/ui/__init__.py
deadline/vred_submitter/ui/components/__init__.py
deadline/vred_submitter/ui/components/constants.py
deadline/vred_submitter/ui/components/scene_settings_callbacks.py
deadline/vred_submitter/ui/components/scene_settings_populator.py
deadline/vred_submitter/ui/components/scene_settings_widget.py
deadline_cloud_for_vred-0.1.5.dist-info/METADATA
deadline_cloud_for_vred-0.1.5.dist-info/WHEEL
deadline_cloud_for_vred-0.1.5.dist-info/entry_points.txt
deadline_cloud_for_vred-0.1.5.dist-info/licenses/LICENSE
deadline_cloud_for_vred-0.1.5.dist-info/licenses/NOTICE
deadline_cloud_for_vred-0.1.5.dist-info/RECORD
