Metadata-Version: 2.4
Name: deadline-cloud-for-vred
Version: 0.1.5
Summary: AWS Deadline Cloud for VRED
Project-URL: Homepage, https://github.com/aws-deadline/deadline-cloud-for-vred
Project-URL: Source, https://github.com/aws-deadline/deadline-cloud-for-vred
License-Expression: Apache-2.0
License-File: LICENSE
License-File: NOTICE
Classifier: Development Status :: 5 - Production/Stable
Classifier: Intended Audience :: Developers
Classifier: Intended Audience :: End Users/Desktop
Classifier: License :: OSI Approved :: Apache Software License
Classifier: Operating System :: Microsoft :: Windows
Classifier: Programming Language :: Python
Classifier: Programming Language :: Python :: 3 :: Only
Classifier: Programming Language :: Python :: 3.11
Classifier: Programming Language :: Python :: 3.12
Requires-Python: >=3.11
Requires-Dist: deadline<0.54,>=0.51.1
